pyinsta3/__init__.py
pyinsta3-1.2.dist-info/LICENSE.txt
pyinsta3-1.2.dist-info/METADATA
pyinsta3-1.2.dist-info/WHEEL
pyinsta3-1.2.dist-info/top_level.txt
pyinsta3-1.2.dist-info/RECORD
