Metadata-Version: 2.1
Name: pyinsta3
Version: 1.2
Summary: pyinsta3 is a package to get instagram profile info of any user.
Home-page: https://www.google.com
Author: toxicrecker
Author-email: reck.channel.mainlead@gmail.com
License: UNKNOWN
Platform: UNKNOWN
Classifier: Programming Language :: Python :: 3
Classifier: License :: OSI Approved :: MIT License
Classifier: Operating System :: OS Independent
Requires-Python: >=3.6
Requires-Dist: aiohttp
